brainframe_apps/__init__.py
brainframe_apps/add_stream.py
brainframe_apps/bf_ca.crt
brainframe_apps/bf_log_print.py
brainframe_apps/capsule_control.py
brainframe_apps/cli.py
brainframe_apps/cognito_defs.py
brainframe_apps/cognito_signin.py
brainframe_apps/command_utils.py
brainframe_apps/delete_stream.py
brainframe_apps/domain_defs.py
brainframe_apps/domain_signin.py
brainframe_apps/fps_report.py
brainframe_apps/get_configuration.py
brainframe_apps/get_zone_statuses.py
brainframe_apps/identity_control.py
brainframe_apps/license_control.py
brainframe_apps/list_stream.py
brainframe_apps/logger_factory.py
brainframe_apps/print_utils.py
brainframe_apps/process_image.py
brainframe_apps/set_configuration.py
brainframe_apps/start_analyzing.py
brainframe_apps/stop_analyzing.py
brainframe_apps/time_utils.py
brainframe_apps/translations/portal.en.yml
brainframe_apps/urls.py
brainframe_apps/user_control.py
brainframe_apps/wait_for_ready.py
brainframe_apps-0.5.4.1.dist-info/COPYING
brainframe_apps-0.5.4.1.dist-info/METADATA
brainframe_apps-0.5.4.1.dist-info/WHEEL
brainframe_apps-0.5.4.1.dist-info/entry_points.txt
brainframe_apps-0.5.4.1.dist-info/RECORD
